Metadata-Version: 2.1
Name: lyydemo
Version: 1.3
Summary: lyydemo for lyy
Author: yy
Author-email: 
License: MIT
License-File: LICENSE
